cam_manager/__init__.py
cam_manager/cam_ai.py
cam_manager/cam_control.py
cam_manager/cam_effects.py
cam_manager/cam_info.py
cam_manager/cam_manager.py
cam_manager/cam_settings.py
cam_manager-0.3.3.dist-info/METADATA
cam_manager-0.3.3.dist-info/WHEEL
cam_manager-0.3.3.dist-info/top_level.txt
cam_manager-0.3.3.dist-info/RECORD
