Metadata-Version: 2.1
Name: cam_manager
Version: 0.3.3
Summary: A camera management library with a wide range of options.
Home-page: https://github.com/snatev/cam-manager
Author: snatev
Author-email: snatev@proton.me
Classifier: Operating System :: OS Independent
Classifier: Programming Language :: Python :: 3
Classifier: License :: OSI Approved :: MIT License
Requires-Python: >=3.6
Requires-Dist: mss ==9.0.1
Requires-Dist: torch ==2.2.2
Requires-Dist: torchaudio ==2.2.2
Requires-Dist: python-xlib ==0.33
Requires-Dist: PyGetWindow ==0.0.9
Requires-Dist: setuptools ==69.5.1
Requires-Dist: torchvision ==0.17.2
Requires-Dist: ultralytics ==8.2.22
Requires-Dist: opencv-python ==4.9.0.80
